ctm/__init__.py
ctm/ctm.py
ctm_py-0.0.1.dist-info/METADATA
ctm_py-0.0.1.dist-info/WHEEL
ctm_py-0.0.1.dist-info/entry_points.txt
ctm_py-0.0.1.dist-info/top_level.txt
ctm_py-0.0.1.dist-info/RECORD
