Metadata-Version: 2.1
Name: ctm-py
Version: 0.0.1
Summary: Cloud Task Manager
Home-page: UNKNOWN
Author: 
Author-email: 
License: UNKNOWN
Keywords: Cloud Task Manager
Platform: UNKNOWN
Classifier: Programming Language :: Python :: 3.7
Requires-Dist: fire
Requires-Dist: pyyaml
Requires-Dist: redis
Requires-Dist: tabulate
